{"frameRate":24,"isGlobal":0,"armature":[{"defaultActions":[{"gotoAndPlay":"boyYellow_run"}],"type":"Armature","ik":[],"skin":[{"slot":[{"display":[{"path":"boyYellow for dragonbones/handR","type":"image","name":"boyYellow for dragonbones/handR","transform":{"y":3.1461,"skX":-74.5942,"skY":-74.5942,"x":11.2289}},{"path":"girlYellow for dragonbones/handR","type":"image","name":"girlYellow for dragonbones/handR","transform":{"y":2.6628,"skX":-74.5942,"skY":-74.5942,"x":13.2396}}],"name":"handR"},{"display":[{"path":"boyYellow for dragonbones/armR","type":"image","name":"boyYellow for dragonbones/armR","transform":{"y":4.883,"skX":-78.9318,"skY":-78.9318,"x":14.5443}},{"path":"boyYellow forward/handL_forward","type":"image","name":"boyYellow forward/handL_forward","transform":{"y":4.6162,"skX":-78.9318,"skY":-78.9318,"x":31.474}},{"path":"girlYellow for dragonbones/armR","type":"image","name":"girlYellow for dragonbones/armR","transform":{"y":3.5077,"skX":-78.9318,"skY":-78.9318,"x":17.9314}},{"path":"girlYellow forward/handL_forward","type":"image","name":"girlYellow forward/handL_forward","transform":{"y":2.8651,"skX":-78.9318,"skY":-78.9318,"x":31.396}}],"name":"armR"},{"display":[{"path":"boyYellow for dragonbones/tight","type":"image","name":"boyYellow for dragonbones/tight","transform":{"y":14.0612,"x":3.75}},{"path":"boyYellow forward/tight_forward","type":"image","name":"boyYellow forward/tight_forward","transform":{"y":38.3748,"x":-3.738}},{"path":"girlYellow for dragonbones/tight","type":"image","name":"girlYellow for dragonbones/tight","transform":{"y":12.1213,"x":4.75}},{"path":"girlYellow forward/tight_forward","type":"image","name":"girlYellow forward/tight_forward","transform":{"y":35.962,"x":-0.7845}}],"name":"tight"},{"display":[{"path":"boyYellow for dragonbones/head","type":"image","name":"boyYellow for dragonbones/head","transform":{"y":-2.4958,"skX":90.5739,"skY":90.5739,"x":40.3658}},{"path":"boyYellow forward/head_forward","type":"image","name":"boyYellow forward/head_forward","transform":{"y":-0.9295,"skX":90.5739,"skY":90.5739,"x":45.7868}},{"path":"girlYellow for dragonbones/head","type":"image","name":"girlYellow for dragonbones/head","transform":{"y":-5.8614,"skX":90.5739,"skY":90.5739,"x":28.8389}},{"path":"girlYellow forward/head_forward","type":"image","name":"girlYellow forward/head_forward","transform":{"y":1.4329,"skX":90.5739,"skY":90.5739,"x":36.6755}}],"name":"head"},{"display":[{"path":"boyYellow for dragonbones/armL","type":"image","name":"boyYellow for dragonbones/armL","transform":{"y":-0.5791,"skX":-92.6984,"skY":-92.6984,"x":13.3488}},{"path":"boyYellow forward/handR_forward","type":"image","name":"boyYellow forward/handR_forward","transform":{"y":-2.3815,"skX":-92.6984,"skY":-92.6984,"x":30.096}},{"path":"girlYellow for dragonbones/armL","type":"image","name":"girlYellow for dragonbones/armL","transform":{"y":-2.5301,"skX":-92.6984,"skY":-92.6984,"x":17.5717}},{"path":"girlYellow forward/handR_forward","type":"image","name":"girlYellow forward/handR_forward","transform":{"y":-6.2027,"skX":-92.6984,"skY":-92.6984,"x":32.5061}}],"name":"armL"},{"display":[{"path":"boyYellow for dragonbones/footR","type":"image","name":"boyYellow for dragonbones/footR","transform":{"y":-3.0739,"skX":-82.2468,"skY":-82.2468,"x":7.444}},{"path":"girlYellow for dragonbones/footR","type":"image","name":"girlYellow for dragonbones/footR","transform":{"y":-4.0555,"skX":-82.2468,"skY":-82.2468,"x":2.0875}}],"name":"footR"},{"display":[{"path":"boyYellow for dragonbones/handL","type":"image","name":"boyYellow for dragonbones/handL","transform":{"y":-0.7896,"skX":-86.3211,"skY":-86.3211,"x":14.9928}},{"path":"girlYellow for dragonbones/handL","type":"image","name":"girlYellow for dragonbones/handL","transform":{"y":-0.481,"skX":-86.3211,"skY":-86.3211,"x":19.7929}}],"name":"handL"},{"display":[{"path":"boyYellow for dragonbones/tightR","type":"image","name":"boyYellow for dragonbones/tightR","transform":{"y":1.8643,"skX":-84.2811,"skY":-84.2811,"x":17.1106}},{"path":"girlYellow for dragonbones/tightR","type":"image","name":"girlYellow for dragonbones/tightR","transform":{"y":3.0639,"skX":-84.2811,"skY":-84.2811,"x":14.0358}}],"name":"tightR"},{"display":[{"path":"boyYellow for dragonbones/tightL","type":"image","name":"boyYellow for dragonbones/tightL","transform":{"y":0.0905,"skX":-92.6356,"skY":-92.6356,"x":15.4317}},{"path":"girlYellow for dragonbones/tightL","type":"image","name":"girlYellow for dragonbones/tightL","transform":{"y":-0.581,"skX":-92.6356,"skY":-92.6356,"x":13.7091}}],"name":"tightL"},{"display":[{"path":"boyYellow for dragonbones/footL","type":"image","name":"boyYellow for dragonbones/footL","transform":{"y":-7.3654,"skX":-79.6857,"skY":-79.6857,"x":15.9375}},{"path":"girlYellow for dragonbones/footL","type":"image","name":"girlYellow for dragonbones/footL","transform":{"y":-8.3616,"skX":-79.6857,"skY":-79.6857,"x":11.8601}}],"name":"footL"},{"display":[{"path":"boyYellow for dragonbones/body","type":"image","name":"boyYellow for dragonbones/body","transform":{"y":2.4559,"skX":90.8323,"skY":90.8323,"x":14.1546}},{"path":"boyYellow forward/body_forward","type":"image","name":"boyYellow forward/body_forward","transform":{"y":3.2677,"skX":90.8323,"skY":90.8323,"x":17.5796}},{"path":"boyYellow left/left","type":"image","name":"boyYellow left/left","transform":{"y":0.2512,"skX":90.8323,"skY":90.8323,"x":17.2929}},{"path":"boyYellow right/right","type":"image","name":"boyYellow right/right","transform":{"y":0.2583,"skX":90.8323,"skY":90.8323,"x":17.777}},{"path":"girlYellow for dragonbones/body","type":"image","name":"girlYellow for dragonbones/body","transform":{"y":3.6903,"skX":90.8323,"skY":90.8323,"x":13.0765}},{"path":"girlYellow forward/body_forward","type":"image","name":"girlYellow forward/body_forward","transform":{"y":4.2125,"skX":90.8323,"skY":90.8323,"x":16.9786}},{"path":"girlYellow left/left","type":"image","name":"girlYellow left/left","transform":{"y":0.4629,"skX":90.8323,"skY":90.8323,"x":14.6546}},{"path":"girlYellow right/right","type":"image","name":"girlYellow right/right","transform":{"y":0.4629,"skX":90.8323,"skY":90.8323,"x":14.6546}}],"name":"body"}],"name":""}],"animation":[{"ik":[],"frame":[],"playTimes":0,"slot":[{"colorFrame":[],"displayFrame":[{"duration":12},{"duration":0}],"name":"head"},{"colorFrame":[],"displayFrame":[{"duration":12},{"duration":0}],"name":"handL"},{"colorFrame":[],"displayFrame":[{"duration":12},{"duration":0}],"name":"armL"},{"colorFrame":[],"displayFrame":[{"duration":12},{"duration":0}],"name":"footL"},{"colorFrame":[],"displayFrame":[{"duration":12},{"duration":0}],"name":"tightL"},{"colorFrame":[],"displayFrame":[{"duration":12},{"duration":0}],"name":"footR"},{"colorFrame":[],"displayFrame":[{"duration":12},{"duration":0}],"name":"tightR"},{"colorFrame":[],"displayFrame":[{"duration":12},{"duration":0}],"name":"body"},{"colorFrame":[],"displayFrame":[{"duration":12},{"duration":0}],"name":"tight"},{"colorFrame":[],"displayFrame":[{"duration":12},{"duration":0}],"name":"handR"},{"colorFrame":[],"displayFrame":[{"duration":12},{"duration":0}],"name":"armR"}],"ffd":[],"zOrder":{"frame":[{"zOrder":[],"tweenEasing":null,"duration":12},{"zOrder":[],"tweenEasing":null,"duration":0}]},"bone":[{"rotateFrame":[],"scaleFrame":[],"name":"root","translateFrame":[{"y":4.3026,"tweenEasing":0,"duration":3},{"y":1.5658,"tweenEasing":0,"duration":3},{"y":10.3192,"tweenEasing":0,"duration":3},{"y":3.6194,"tweenEasing":0,"duration":3},{"y":4.3026,"duration":0}]},{"rotateFrame":[{"tweenEasing":0,"duration":12,"rotate":9.9859},{"duration":0,"rotate":9.9859}],"scaleFrame":[],"name":"body","translateFrame":[{"y":3.7784,"tweenEasing":0,"duration":3,"x":0.9497},{"y":1.4245,"tweenEasing":0,"duration":3},{"y":2.916,"tweenEasing":0,"duration":3},{"y":2.3742,"tweenEasing":0,"duration":3},{"y":3.7784,"duration":0,"x":0.9497}]},{"rotateFrame":[],"scaleFrame":[],"name":"bone","translateFrame":[]},{"rotateFrame":[{"tweenEasing":0,"duration":6,"rotate":-311.3105},{"tweenEasing":0,"duration":6,"rotate":-26.1117},{"duration":0,"rotate":-311.3105}],"scaleFrame":[],"name":"armR","translateFrame":[{"y":3.9227,"tweenEasing":0,"duration":6,"x":-5.5593},{"y":-4.1391,"tweenEasing":0,"duration":6,"x":2.7816},{"y":3.9227,"duration":0,"x":-5.5593}]},{"rotateFrame":[{"tweenEasing":0,"duration":6},{"tweenEasing":0,"duration":6,"rotate":2.1228},{"duration":0}],"scaleFrame":[],"name":"head","translateFrame":[{"y":-0.476,"tweenEasing":0,"duration":12,"x":0.3017},{"y":-0.476,"duration":0,"x":0.3017}]},{"rotateFrame":[{"tweenEasing":0,"duration":6,"rotate":341.671},{"tweenEasing":0,"duration":6,"rotate":6.7472},{"duration":0,"rotate":341.671}],"scaleFrame":[],"name":"armL","translateFrame":[{"y":0.261,"tweenEasing":0,"duration":3,"x":-2.3412},{"y":0.1901,"tweenEasing":0,"duration":3,"x":-2.5481},{"y":-0.2091,"tweenEasing":0,"duration":3,"x":-5.4881},{"y":0.2399,"tweenEasing":0,"duration":3,"x":-2.5401},{"y":0.261,"duration":0,"x":-2.3412}]},{"rotateFrame":[{"tweenEasing":0,"duration":3,"rotate":19.3849},{"tweenEasing":0,"duration":3,"rotate":-17.5617},{"tweenEasing":0,"duration":3,"rotate":-50.1169},{"tweenEasing":0,"duration":3,"rotate":-10.4916},{"duration":0,"rotate":19.3849}],"scaleFrame":[],"name":"tightL","translateFrame":[{"y":-1.2561,"tweenEasing":0,"duration":3},{"y":1.0268,"tweenEasing":0,"duration":3,"x":-1.7113},{"y":5.791,"tweenEasing":0,"duration":3},{"y":0.3149,"tweenEasing":0,"duration":3,"x":-2.0536},{"y":-1.2561,"duration":0}]},{"rotateFrame":[{"tweenEasing":0,"duration":3,"rotate":-18.6244},{"tweenEasing":0,"duration":3,"rotate":3.6569},{"tweenEasing":0,"duration":3,"rotate":49.459},{"tweenEasing":0,"duration":3,"rotate":14.0294},{"duration":0,"rotate":-18.6244}],"scaleFrame":[],"name":"tightR","translateFrame":[{"y":4.547,"tweenEasing":0,"duration":3},{"tweenEasing":0,"duration":3,"x":-1.7113},{"y":-6.3174,"tweenEasing":0,"duration":3,"x":8.2632},{"y":-1.0268,"tweenEasing":0,"duration":3,"x":-0.6845},{"y":4.547,"duration":0}]},{"rotateFrame":[{"tweenEasing":0,"duration":3,"rotate":-2.759},{"tweenEasing":0,"duration":3,"rotate":-0.3082},{"tweenEasing":0,"duration":6,"rotate":27.957},{"duration":0,"rotate":-2.759}],"scaleFrame":[],"name":"footR","translateFrame":[{"y":2.4026,"tweenEasing":0,"duration":6,"x":-1.087},{"y":3.7796,"tweenEasing":0,"duration":3,"x":-0.0758},{"y":0.2968,"tweenEasing":0,"duration":3,"x":-2.032},{"y":2.4026,"duration":0,"x":-1.087}]},{"rotateFrame":[{"tweenEasing":0,"duration":12,"rotate":-27.352},{"duration":0,"rotate":-27.352}],"scaleFrame":[],"name":"handR","translateFrame":[{"y":-4.2993,"tweenEasing":0,"duration":12,"x":-1.3573},{"y":-4.2993,"duration":0,"x":-1.3573}]},{"rotateFrame":[{"tweenEasing":0,"duration":12,"rotate":-28.5136},{"duration":0,"rotate":-28.5136}],"scaleFrame":[],"name":"handL","translateFrame":[{"y":-1.5016,"tweenEasing":0,"duration":6,"x":0.7993},{"y":-2.6495,"tweenEasing":0,"duration":6,"x":2.0027},{"y":-1.5016,"duration":0,"x":0.7993}]},{"rotateFrame":[{"tweenEasing":0,"duration":3,"rotate":28.5617},{"tweenEasing":0,"duration":3,"rotate":36.3203},{"tweenEasing":0,"duration":3,"rotate":11.1914},{"tweenEasing":0,"duration":3,"rotate":11.3522},{"duration":0,"rotate":28.5617}],"scaleFrame":[],"name":"footL","translateFrame":[{"y":-2.2385,"tweenEasing":0,"duration":12,"x":-1.0305},{"y":-2.2385,"duration":0,"x":-1.0305}]}],"name":"boyYellow_run","duration":12},{"ik":[],"frame":[],"playTimes":0,"slot":[{"colorFrame":[],"displayFrame":[{"value":-1,"duration":1},{"value":-1,"duration":0}],"name":"handL"},{"colorFrame":[],"displayFrame":[{"value":-1,"duration":1},{"value":-1,"duration":0}],"name":"armL"},{"colorFrame":[],"displayFrame":[{"value":-1,"duration":1},{"value":-1,"duration":0}],"name":"footL"},{"colorFrame":[],"displayFrame":[{"value":-1,"duration":1},{"value":-1,"duration":0}],"name":"tightL"},{"colorFrame":[],"displayFrame":[{"value":-1,"duration":1},{"value":-1,"duration":0}],"name":"footR"},{"colorFrame":[],"displayFrame":[{"value":-1,"duration":1},{"value":-1,"duration":0}],"name":"tightR"},{"colorFrame":[],"displayFrame":[{"value":-1,"duration":1},{"value":-1,"duration":0}],"name":"tight"},{"colorFrame":[],"displayFrame":[{"value":2,"duration":1},{"value":2,"duration":0}],"name":"body"},{"colorFrame":[],"displayFrame":[{"value":-1,"duration":1},{"value":-1,"duration":0}],"name":"handR"},{"colorFrame":[],"displayFrame":[{"value":-1,"duration":1},{"value":-1,"duration":0}],"name":"armR"},{"colorFrame":[],"displayFrame":[{"value":-1,"duration":1},{"value":-1,"duration":0}],"name":"head"}],"ffd":[],"bone":[{"rotateFrame":[],"scaleFrame":[],"name":"root","translateFrame":[]},{"rotateFrame":[],"scaleFrame":[],"name":"body","translateFrame":[]},{"rotateFrame":[],"scaleFrame":[],"name":"bone","translateFrame":[]},{"rotateFrame":[],"scaleFrame":[],"name":"armR","translateFrame":[]},{"rotateFrame":[],"scaleFrame":[],"name":"head","translateFrame":[]},{"rotateFrame":[],"scaleFrame":[],"name":"armL","translateFrame":[]},{"rotateFrame":[],"scaleFrame":[],"name":"tightL","translateFrame":[]},{"rotateFrame":[],"scaleFrame":[],"name":"tightR","translateFrame":[]},{"rotateFrame":[],"scaleFrame":[],"name":"handL","translateFrame":[]},{"rotateFrame":[],"scaleFrame":[],"name":"handR","translateFrame":[]},{"rotateFrame":[],"scaleFrame":[],"name":"footR","translateFrame":[]},{"rotateFrame":[],"scaleFrame":[],"name":"footL","translateFrame":[]}],"name":"boyYellow_left","duration":1},{"ik":[],"frame":[],"playTimes":0,"slot":[{"colorFrame":[],"displayFrame":[{"value":1,"duration":24},{"value":1,"duration":0}],"name":"head"},{"colorFrame":[],"displayFrame":[{"value":-1,"duration":24},{"value":-1,"duration":0}],"name":"handL"},{"colorFrame":[],"displayFrame":[{"value":1,"duration":24},{"value":1,"duration":0}],"name":"armL"},{"colorFrame":[],"displayFrame":[{"value":-1,"duration":24},{"value":-1,"duration":0}],"name":"footL"},{"colorFrame":[],"displayFrame":[{"value":-1,"duration":24},{"value":-1,"duration":0}],"name":"tightL"},{"colorFrame":[],"displayFrame":[{"value":-1,"duration":24},{"value":-1,"duration":0}],"name":"footR"},{"colorFrame":[],"displayFrame":[{"value":-1,"duration":24},{"value":-1,"duration":0}],"name":"tightR"},{"colorFrame":[],"displayFrame":[{"value":1,"duration":24},{"value":1,"duration":0}],"name":"tight"},{"colorFrame":[],"displayFrame":[{"value":1,"duration":24},{"value":1,"duration":0}],"name":"body"},{"colorFrame":[],"displayFrame":[{"value":-1,"duration":24},{"value":-1,"duration":0}],"name":"handR"},{"colorFrame":[],"displayFrame":[{"value":1,"duration":24},{"value":1,"duration":0}],"name":"armR"}],"ffd":[],"zOrder":{"frame":[{"zOrder":[],"tweenEasing":null,"duration":24},{"zOrder":[],"tweenEasing":null,"duration":0}]},"bone":[{"rotateFrame":[{"tweenEasing":0,"duration":24},{"duration":0}],"scaleFrame":[],"name":"root","translateFrame":[{"y":1.3819,"tweenEasing":0,"duration":24},{"y":1.3819,"duration":0}]},{"rotateFrame":[{"tweenEasing":0,"duration":24},{"duration":0}],"scaleFrame":[],"name":"body","translateFrame":[{"tweenEasing":0,"duration":12},{"y":1.938,"tweenEasing":0,"duration":12},{"duration":0}]},{"rotateFrame":[{"tweenEasing":0,"duration":24},{"duration":0}],"scaleFrame":[],"name":"bone","translateFrame":[{"tweenEasing":0,"duration":24},{"duration":0}]},{"rotateFrame":[{"tweenEasing":0,"duration":12},{"tweenEasing":0,"duration":12,"rotate":3.8166},{"duration":0}],"scaleFrame":[],"name":"armR","translateFrame":[{"tweenEasing":0,"duration":24},{"duration":0}]},{"rotateFrame":[{"tweenEasing":0,"duration":24},{"duration":0}],"scaleFrame":[],"name":"head","translateFrame":[{"tweenEasing":0,"duration":12},{"y":-0.0211,"tweenEasing":0,"duration":12,"x":-1.4533},{"duration":0}]},{"rotateFrame":[{"tweenEasing":0,"duration":12},{"tweenEasing":0,"duration":12,"rotate":354.1616},{"duration":0}],"scaleFrame":[],"name":"armL","translateFrame":[{"tweenEasing":0,"duration":24},{"duration":0}]},{"rotateFrame":[{"tweenEasing":0,"duration":24},{"duration":0}],"scaleFrame":[],"name":"tightL","translateFrame":[{"tweenEasing":0,"duration":24},{"duration":0}]},{"rotateFrame":[{"tweenEasing":0,"duration":24},{"duration":0}],"scaleFrame":[],"name":"tightR","translateFrame":[{"tweenEasing":0,"duration":24},{"duration":0}]},{"rotateFrame":[{"tweenEasing":0,"duration":24},{"duration":0}],"scaleFrame":[],"name":"footR","translateFrame":[{"tweenEasing":0,"duration":24},{"duration":0}]},{"rotateFrame":[{"tweenEasing":0,"duration":24},{"duration":0}],"scaleFrame":[],"name":"handR","translateFrame":[{"tweenEasing":0,"duration":24},{"duration":0}]},{"rotateFrame":[{"tweenEasing":0,"duration":24},{"duration":0}],"scaleFrame":[],"name":"handL","translateFrame":[{"tweenEasing":0,"duration":24},{"duration":0}]},{"rotateFrame":[{"tweenEasing":0,"duration":24},{"duration":0}],"scaleFrame":[],"name":"footL","translateFrame":[{"tweenEasing":0,"duration":24},{"duration":0}]}],"name":"boyYellow_idle2","duration":24},{"ik":[],"frame":[],"playTimes":0,"slot":[{"colorFrame":[],"displayFrame":[{"duration":24},{"duration":0}],"name":"head"},{"colorFrame":[],"displayFrame":[{"duration":24},{"duration":0}],"name":"handL"},{"colorFrame":[],"displayFrame":[{"duration":24},{"duration":0}],"name":"armL"},{"colorFrame":[],"displayFrame":[{"duration":24},{"duration":0}],"name":"footL"},{"colorFrame":[],"displayFrame":[{"duration":24},{"duration":0}],"name":"tightL"},{"colorFrame":[],"displayFrame":[{"duration":24},{"duration":0}],"name":"footR"},{"colorFrame":[],"displayFrame":[{"duration":24},{"duration":0}],"name":"tightR"},{"colorFrame":[],"displayFrame":[{"duration":24},{"duration":0}],"name":"tight"},{"colorFrame":[],"displayFrame":[{"duration":24},{"duration":0}],"name":"body"},{"colorFrame":[],"displayFrame":[{"duration":24},{"duration":0}],"name":"handR"},{"colorFrame":[],"displayFrame":[{"duration":24},{"duration":0}],"name":"armR"}],"ffd":[],"zOrder":{"frame":[{"zOrder":[],"tweenEasing":null,"duration":24},{"zOrder":[],"tweenEasing":null,"duration":0}]},"bone":[{"rotateFrame":[{"tweenEasing":0,"duration":24},{"duration":0}],"scaleFrame":[],"name":"root","translateFrame":[{"tweenEasing":0,"duration":24},{"duration":0}]},{"rotateFrame":[{"tweenEasing":0,"duration":24},{"duration":0}],"scaleFrame":[],"name":"body","translateFrame":[{"tweenEasing":0,"duration":12},{"y":1.938,"tweenEasing":0,"duration":12},{"duration":0}]},{"rotateFrame":[{"tweenEasing":0,"duration":24},{"duration":0}],"scaleFrame":[],"name":"bone","translateFrame":[{"tweenEasing":0,"duration":24},{"duration":0}]},{"rotateFrame":[{"tweenEasing":0,"duration":12},{"tweenEasing":0,"duration":12,"rotate":3.8166},{"duration":0}],"scaleFrame":[],"name":"armR","translateFrame":[{"tweenEasing":0,"duration":24},{"duration":0}]},{"rotateFrame":[{"tweenEasing":0,"duration":24},{"duration":0}],"scaleFrame":[],"name":"head","translateFrame":[{"y":0.6778,"tweenEasing":0,"duration":12,"x":0.0505},{"y":0.6662,"tweenEasing":0,"duration":12,"x":-0.7467},{"y":0.6778,"duration":0,"x":0.0505}]},{"rotateFrame":[{"tweenEasing":0,"duration":12},{"tweenEasing":0,"duration":12,"rotate":354.1616},{"duration":0}],"scaleFrame":[],"name":"armL","translateFrame":[{"tweenEasing":0,"duration":24},{"duration":0}]},{"rotateFrame":[{"tweenEasing":0,"duration":24},{"duration":0}],"scaleFrame":[],"name":"tightL","translateFrame":[{"tweenEasing":0,"duration":24},{"duration":0}]},{"rotateFrame":[{"tweenEasing":0,"duration":24},{"duration":0}],"scaleFrame":[],"name":"tightR","translateFrame":[{"tweenEasing":0,"duration":24},{"duration":0}]},{"rotateFrame":[{"tweenEasing":0,"duration":24},{"duration":0}],"scaleFrame":[],"name":"footR","translateFrame":[{"tweenEasing":0,"duration":24},{"duration":0}]},{"rotateFrame":[{"tweenEasing":0,"duration":24},{"duration":0}],"scaleFrame":[],"name":"handR","translateFrame":[{"tweenEasing":0,"duration":24},{"duration":0}]},{"rotateFrame":[{"tweenEasing":0,"duration":24},{"duration":0}],"scaleFrame":[],"name":"handL","translateFrame":[{"y":0.6224,"tweenEasing":0,"duration":24,"x":0.0293},{"y":0.6224,"duration":0,"x":0.0293}]},{"rotateFrame":[{"tweenEasing":0,"duration":24},{"duration":0}],"scaleFrame":[],"name":"footL","translateFrame":[{"tweenEasing":0,"duration":24},{"duration":0}]}],"name":"boyYellow_idle1","duration":24},{"ik":[],"frame":[],"playTimes":0,"slot":[{"colorFrame":[],"displayFrame":[{"value":-1,"duration":1},{"value":-1,"duration":0}],"name":"handL"},{"colorFrame":[],"displayFrame":[{"value":-1,"duration":1},{"value":-1,"duration":0}],"name":"armL"},{"colorFrame":[],"displayFrame":[{"value":-1,"duration":1},{"value":-1,"duration":0}],"name":"footL"},{"colorFrame":[],"displayFrame":[{"value":-1,"duration":1},{"value":-1,"duration":0}],"name":"tightL"},{"colorFrame":[],"displayFrame":[{"value":-1,"duration":1},{"value":-1,"duration":0}],"name":"footR"},{"colorFrame":[],"displayFrame":[{"value":-1,"duration":1},{"value":-1,"duration":0}],"name":"tightR"},{"colorFrame":[],"displayFrame":[{"value":-1,"duration":1},{"value":-1,"duration":0}],"name":"tight"},{"colorFrame":[],"displayFrame":[{"value":3,"duration":1},{"value":3,"duration":0}],"name":"body"},{"colorFrame":[],"displayFrame":[{"value":-1,"duration":1},{"value":-1,"duration":0}],"name":"handR"},{"colorFrame":[],"displayFrame":[{"value":-1,"duration":1},{"value":-1,"duration":0}],"name":"armR"},{"colorFrame":[],"displayFrame":[{"value":-1,"duration":1},{"value":-1,"duration":0}],"name":"head"}],"ffd":[],"bone":[{"rotateFrame":[],"scaleFrame":[],"name":"root","translateFrame":[]},{"rotateFrame":[],"scaleFrame":[],"name":"body","translateFrame":[]},{"rotateFrame":[],"scaleFrame":[],"name":"bone","translateFrame":[]},{"rotateFrame":[],"scaleFrame":[],"name":"armR","translateFrame":[]},{"rotateFrame":[],"scaleFrame":[],"name":"head","translateFrame":[]},{"rotateFrame":[],"scaleFrame":[],"name":"armL","translateFrame":[]},{"rotateFrame":[],"scaleFrame":[],"name":"tightL","translateFrame":[]},{"rotateFrame":[],"scaleFrame":[],"name":"tightR","translateFrame":[]},{"rotateFrame":[],"scaleFrame":[],"name":"handL","translateFrame":[]},{"rotateFrame":[],"scaleFrame":[],"name":"handR","translateFrame":[]},{"rotateFrame":[],"scaleFrame":[],"name":"footR","translateFrame":[]},{"rotateFrame":[],"scaleFrame":[],"name":"footL","translateFrame":[]}],"name":"boyYellow_right","duration":1},{"ik":[],"frame":[],"playTimes":0,"slot":[{"colorFrame":[],"displayFrame":[{"value":2,"duration":12},{"value":2,"duration":0}],"name":"head"},{"colorFrame":[],"displayFrame":[{"value":1,"duration":12},{"value":1,"duration":0}],"name":"handL"},{"colorFrame":[],"displayFrame":[{"value":2,"duration":12},{"value":2,"duration":0}],"name":"armL"},{"colorFrame":[],"displayFrame":[{"value":1,"duration":12},{"value":1,"duration":0}],"name":"footL"},{"colorFrame":[],"displayFrame":[{"value":1,"duration":12},{"value":1,"duration":0}],"name":"tightL"},{"colorFrame":[],"displayFrame":[{"value":1,"duration":12},{"value":1,"duration":0}],"name":"footR"},{"colorFrame":[],"displayFrame":[{"value":1,"duration":12},{"value":1,"duration":0}],"name":"tightR"},{"colorFrame":[],"displayFrame":[{"value":4,"duration":12},{"value":4,"duration":0}],"name":"body"},{"colorFrame":[],"displayFrame":[{"value":2,"duration":12},{"value":2,"duration":0}],"name":"tight"},{"colorFrame":[],"displayFrame":[{"value":1,"duration":12},{"value":1,"duration":0}],"name":"handR"},{"colorFrame":[],"displayFrame":[{"value":2,"duration":12},{"value":2,"duration":0}],"name":"armR"}],"ffd":[],"zOrder":{"frame":[{"zOrder":[],"tweenEasing":null,"duration":12},{"zOrder":[],"tweenEasing":null,"duration":0}]},"bone":[{"rotateFrame":[],"scaleFrame":[],"name":"root","translateFrame":[{"y":3.6762,"tweenEasing":0,"duration":3},{"y":0.6262,"tweenEasing":0,"duration":3},{"y":1.1574,"tweenEasing":0,"duration":3},{"y":4.5591,"tweenEasing":0,"duration":3},{"y":3.9894,"duration":0}]},{"rotateFrame":[{"tweenEasing":0,"duration":12,"rotate":9.9859},{"duration":0,"rotate":9.9859}],"scaleFrame":[],"name":"body","translateFrame":[{"y":3.7784,"tweenEasing":0,"duration":3,"x":0.9497},{"y":1.4245,"tweenEasing":0,"duration":3},{"y":2.916,"tweenEasing":0,"duration":3},{"y":2.3742,"tweenEasing":0,"duration":3},{"y":3.7784,"duration":0,"x":0.9497}]},{"rotateFrame":[],"scaleFrame":[],"name":"bone","translateFrame":[]},{"rotateFrame":[{"tweenEasing":0,"duration":6,"rotate":-318.3401},{"tweenEasing":0,"duration":6,"rotate":-26.1117},{"duration":0,"rotate":-318.3401}],"scaleFrame":[],"name":"armR","translateFrame":[{"y":1.6404,"tweenEasing":0,"duration":3,"x":-5.628},{"y":-2.2803,"tweenEasing":0,"duration":3,"x":-1.295},{"y":-11.3518,"tweenEasing":0,"duration":3,"x":0.3465},{"y":-1.8258,"tweenEasing":0,"duration":3,"x":-1.2803},{"y":1.6404,"duration":0,"x":-5.628}]},{"rotateFrame":[{"tweenEasing":0,"duration":6},{"tweenEasing":0,"duration":6,"rotate":2.1228},{"duration":0}],"scaleFrame":[],"name":"head","translateFrame":[{"y":-0.476,"tweenEasing":0,"duration":12,"x":0.3017},{"y":-0.476,"duration":0,"x":0.3017}]},{"rotateFrame":[{"tweenEasing":0,"duration":6,"rotate":341.671},{"tweenEasing":0,"duration":6,"rotate":6.7472},{"duration":0,"rotate":341.671}],"scaleFrame":[],"name":"armL","translateFrame":[{"y":-0.3026,"tweenEasing":0,"duration":3,"x":1.1566},{"y":-0.2434,"tweenEasing":0,"duration":3,"x":0.1422},{"y":-0.2252,"tweenEasing":0,"duration":3,"x":-0.391},{"y":-0.1358,"tweenEasing":0,"duration":3,"x":-0.2085},{"y":-0.3026,"duration":0,"x":1.1566}]},{"rotateFrame":[{"tweenEasing":0,"duration":3,"rotate":19.3849},{"tweenEasing":0,"duration":3,"rotate":-17.5617},{"tweenEasing":0,"duration":3,"rotate":-50.1169},{"tweenEasing":0,"duration":3,"rotate":-10.4916},{"duration":0,"rotate":19.3849}],"scaleFrame":[],"name":"tightL","translateFrame":[{"y":-5.1891,"tweenEasing":0,"duration":3},{"y":3.0705,"tweenEasing":0,"duration":3,"x":-1.7113},{"y":8.5074,"tweenEasing":0,"duration":3},{"y":1.0666,"tweenEasing":0,"duration":3,"x":-2.0536},{"y":-5.1891,"duration":0}]},{"rotateFrame":[{"tweenEasing":0,"duration":3,"rotate":-18.6244},{"tweenEasing":0,"duration":3,"rotate":3.6569},{"tweenEasing":0,"duration":3,"rotate":25.4369},{"tweenEasing":0,"duration":3,"rotate":14.0294},{"duration":0,"rotate":-18.6244}],"scaleFrame":[],"name":"tightR","translateFrame":[{"y":2.2996,"tweenEasing":0,"duration":3},{"tweenEasing":0,"duration":3,"x":-1.7113},{"y":-6.0948,"tweenEasing":0,"duration":3,"x":3.1001},{"y":-1.0268,"tweenEasing":0,"duration":3,"x":-0.6845},{"y":2.2996,"duration":0}]},{"rotateFrame":[{"tweenEasing":0,"duration":3,"rotate":-2.759},{"tweenEasing":0,"duration":3,"rotate":-0.3082},{"tweenEasing":0,"duration":6,"rotate":27.957},{"duration":0,"rotate":-2.759}],"scaleFrame":[],"name":"footR","translateFrame":[{"y":-0.4128,"tweenEasing":0,"duration":3,"x":0.1868},{"y":0.0083,"tweenEasing":0,"duration":3,"x":0.9588},{"y":8.0544,"tweenEasing":0,"duration":3,"x":1.4563},{"y":3.5325,"tweenEasing":0,"duration":3,"x":-1.5594},{"y":-0.4128,"duration":0,"x":0.1868}]},{"rotateFrame":[{"tweenEasing":0,"duration":12,"rotate":-27.352},{"duration":0,"rotate":-27.352}],"scaleFrame":[],"name":"handR","translateFrame":[{"y":-2.2158,"tweenEasing":0,"duration":6,"x":0.9249},{"y":-0.9478,"tweenEasing":0,"duration":6,"x":-1.403},{"y":-2.2158,"duration":0,"x":0.9249}]},{"rotateFrame":[{"tweenEasing":0,"duration":12,"rotate":-28.5136},{"duration":0,"rotate":-28.5136}],"scaleFrame":[],"name":"handL","translateFrame":[{"y":-1.5016,"tweenEasing":0,"duration":6,"x":0.7993},{"y":1.3577,"tweenEasing":0,"duration":6,"x":3.4163},{"y":-1.5016,"duration":0,"x":0.7993}]},{"rotateFrame":[{"tweenEasing":0,"duration":3,"rotate":28.5617},{"tweenEasing":0,"duration":3,"rotate":36.3203},{"tweenEasing":0,"duration":3,"rotate":11.1914},{"tweenEasing":0,"duration":3,"rotate":11.3522},{"duration":0,"rotate":28.5617}],"scaleFrame":[],"name":"footL","translateFrame":[{"y":2.1889,"tweenEasing":0,"duration":3,"x":0.7601},{"y":3.3309,"tweenEasing":0,"duration":3,"x":-0.4044},{"y":0.2601,"tweenEasing":0,"duration":6,"x":-0.4459},{"y":2.1889,"duration":0,"x":0.7601}]}],"name":"girlYellow_run","duration":12},{"ik":[],"frame":[],"playTimes":0,"slot":[{"colorFrame":[],"displayFrame":[{"value":2,"duration":24},{"value":2,"duration":0}],"name":"head"},{"colorFrame":[],"displayFrame":[{"value":1,"duration":24},{"value":1,"duration":0}],"name":"handL"},{"colorFrame":[],"displayFrame":[{"value":2,"duration":24},{"value":2,"duration":0}],"name":"armL"},{"colorFrame":[],"displayFrame":[{"value":1,"duration":24},{"value":1,"duration":0}],"name":"footL"},{"colorFrame":[],"displayFrame":[{"value":1,"duration":24},{"value":1,"duration":0}],"name":"tightL"},{"colorFrame":[],"displayFrame":[{"value":1,"duration":24},{"value":1,"duration":0}],"name":"footR"},{"colorFrame":[],"displayFrame":[{"value":1,"duration":24},{"value":1,"duration":0}],"name":"tightR"},{"colorFrame":[],"displayFrame":[{"value":2,"duration":24},{"value":2,"duration":0}],"name":"tight"},{"colorFrame":[],"displayFrame":[{"value":4,"duration":24},{"value":4,"duration":0}],"name":"body"},{"colorFrame":[],"displayFrame":[{"value":1,"duration":24},{"value":1,"duration":0}],"name":"handR"},{"colorFrame":[],"displayFrame":[{"value":2,"duration":24},{"value":2,"duration":0}],"name":"armR"}],"ffd":[],"zOrder":{"frame":[{"zOrder":[],"tweenEasing":null,"duration":24},{"zOrder":[],"tweenEasing":null,"duration":0}]},"bone":[{"rotateFrame":[{"tweenEasing":0,"duration":24},{"duration":0}],"scaleFrame":[],"name":"root","translateFrame":[{"tweenEasing":0,"duration":24},{"duration":0}]},{"rotateFrame":[{"tweenEasing":0,"duration":24},{"duration":0}],"scaleFrame":[],"name":"body","translateFrame":[{"tweenEasing":0,"duration":12},{"y":1.938,"tweenEasing":0,"duration":12},{"duration":0}]},{"rotateFrame":[{"tweenEasing":0,"duration":24},{"duration":0}],"scaleFrame":[],"name":"bone","translateFrame":[{"tweenEasing":0,"duration":24},{"duration":0}]},{"rotateFrame":[{"tweenEasing":0,"duration":12},{"tweenEasing":0,"duration":12,"rotate":3.8166},{"duration":0}],"scaleFrame":[],"name":"armR","translateFrame":[{"y":-2.5341,"tweenEasing":0,"duration":24,"x":0.0368},{"y":-2.5341,"duration":0,"x":0.0368}]},{"rotateFrame":[{"tweenEasing":0,"duration":24},{"duration":0}],"scaleFrame":[],"name":"head","translateFrame":[{"y":0.6778,"tweenEasing":0,"duration":12,"x":0.0505},{"y":0.6662,"tweenEasing":0,"duration":12,"x":-0.7467},{"y":0.6778,"duration":0,"x":0.0505}]},{"rotateFrame":[{"tweenEasing":0,"duration":12},{"tweenEasing":0,"duration":12,"rotate":354.1616},{"duration":0}],"scaleFrame":[],"name":"armL","translateFrame":[{"tweenEasing":0,"duration":24},{"duration":0}]},{"rotateFrame":[{"tweenEasing":0,"duration":24},{"duration":0}],"scaleFrame":[],"name":"tightL","translateFrame":[{"tweenEasing":0,"duration":24},{"duration":0}]},{"rotateFrame":[{"tweenEasing":0,"duration":24},{"duration":0}],"scaleFrame":[],"name":"tightR","translateFrame":[{"tweenEasing":0,"duration":24},{"duration":0}]},{"rotateFrame":[{"tweenEasing":0,"duration":24},{"duration":0}],"scaleFrame":[],"name":"footR","translateFrame":[{"tweenEasing":0,"duration":24},{"duration":0}]},{"rotateFrame":[{"tweenEasing":0,"duration":24},{"duration":0}],"scaleFrame":[],"name":"handR","translateFrame":[{"tweenEasing":0,"duration":24},{"duration":0}]},{"rotateFrame":[{"tweenEasing":0,"duration":24},{"duration":0}],"scaleFrame":[],"name":"handL","translateFrame":[{"y":0.6224,"tweenEasing":0,"duration":24,"x":0.0293},{"y":0.6224,"duration":0,"x":0.0293}]},{"rotateFrame":[{"tweenEasing":0,"duration":24},{"duration":0}],"scaleFrame":[],"name":"footL","translateFrame":[{"tweenEasing":0,"duration":24},{"duration":0}]}],"name":"girlYellow_idle1","duration":24},{"ik":[],"frame":[],"playTimes":0,"slot":[{"colorFrame":[],"displayFrame":[{"value":3,"duration":24},{"value":3,"duration":0}],"name":"head"},{"colorFrame":[],"displayFrame":[{"value":-1,"duration":24},{"value":-1,"duration":0}],"name":"handL"},{"colorFrame":[],"displayFrame":[{"value":3,"duration":24},{"value":3,"duration":0}],"name":"armL"},{"colorFrame":[],"displayFrame":[{"value":-1,"duration":24},{"value":-1,"duration":0}],"name":"footL"},{"colorFrame":[],"displayFrame":[{"value":-1,"duration":24},{"value":-1,"duration":0}],"name":"tightL"},{"colorFrame":[],"displayFrame":[{"value":-1,"duration":24},{"value":-1,"duration":0}],"name":"footR"},{"colorFrame":[],"displayFrame":[{"value":-1,"duration":24},{"value":-1,"duration":0}],"name":"tightR"},{"colorFrame":[],"displayFrame":[{"value":3,"duration":24},{"value":3,"duration":0}],"name":"tight"},{"colorFrame":[],"displayFrame":[{"value":5,"duration":24},{"value":5,"duration":0}],"name":"body"},{"colorFrame":[],"displayFrame":[{"value":-1,"duration":24},{"value":-1,"duration":0}],"name":"handR"},{"colorFrame":[],"displayFrame":[{"value":3,"duration":24},{"value":3,"duration":0}],"name":"armR"}],"ffd":[],"zOrder":{"frame":[{"zOrder":[],"tweenEasing":null,"duration":24},{"zOrder":[],"tweenEasing":null,"duration":0}]},"bone":[{"rotateFrame":[{"tweenEasing":0,"duration":24},{"duration":0}],"scaleFrame":[],"name":"root","translateFrame":[{"y":1.3819,"tweenEasing":0,"duration":24},{"y":1.3819,"duration":0}]},{"rotateFrame":[{"tweenEasing":0,"duration":24},{"duration":0}],"scaleFrame":[],"name":"body","translateFrame":[{"tweenEasing":0,"duration":12},{"y":1.938,"tweenEasing":0,"duration":12},{"duration":0}]},{"rotateFrame":[{"tweenEasing":0,"duration":24},{"duration":0}],"scaleFrame":[],"name":"bone","translateFrame":[{"tweenEasing":0,"duration":24},{"duration":0}]},{"rotateFrame":[{"tweenEasing":0,"duration":12},{"tweenEasing":0,"duration":12,"rotate":3.8166},{"duration":0}],"scaleFrame":[],"name":"armR","translateFrame":[{"tweenEasing":0,"duration":24},{"duration":0}]},{"rotateFrame":[{"tweenEasing":0,"duration":24},{"duration":0}],"scaleFrame":[],"name":"head","translateFrame":[{"tweenEasing":0,"duration":12},{"y":-0.0211,"tweenEasing":0,"duration":12,"x":-1.4533},{"duration":0}]},{"rotateFrame":[{"tweenEasing":0,"duration":12},{"tweenEasing":0,"duration":12,"rotate":354.1616},{"duration":0}],"scaleFrame":[],"name":"armL","translateFrame":[{"tweenEasing":0,"duration":24},{"duration":0}]},{"rotateFrame":[{"tweenEasing":0,"duration":24},{"duration":0}],"scaleFrame":[],"name":"tightL","translateFrame":[{"tweenEasing":0,"duration":24},{"duration":0}]},{"rotateFrame":[{"tweenEasing":0,"duration":24},{"duration":0}],"scaleFrame":[],"name":"tightR","translateFrame":[{"tweenEasing":0,"duration":24},{"duration":0}]},{"rotateFrame":[{"tweenEasing":0,"duration":24},{"duration":0}],"scaleFrame":[],"name":"footR","translateFrame":[{"tweenEasing":0,"duration":24},{"duration":0}]},{"rotateFrame":[{"tweenEasing":0,"duration":24},{"duration":0}],"scaleFrame":[],"name":"handR","translateFrame":[{"tweenEasing":0,"duration":24},{"duration":0}]},{"rotateFrame":[{"tweenEasing":0,"duration":24},{"duration":0}],"scaleFrame":[],"name":"handL","translateFrame":[{"tweenEasing":0,"duration":24},{"duration":0}]},{"rotateFrame":[{"tweenEasing":0,"duration":24},{"duration":0}],"scaleFrame":[],"name":"footL","translateFrame":[{"tweenEasing":0,"duration":24},{"duration":0}]}],"name":"girlYellow_idle2","duration":24},{"ik":[],"frame":[],"playTimes":0,"slot":[{"colorFrame":[],"displayFrame":[{"value":-1,"duration":1},{"value":-1,"duration":0}],"name":"handL"},{"colorFrame":[],"displayFrame":[{"value":-1,"duration":1},{"value":-1,"duration":0}],"name":"armL"},{"colorFrame":[],"displayFrame":[{"value":-1,"duration":1},{"value":-1,"duration":0}],"name":"footL"},{"colorFrame":[],"displayFrame":[{"value":-1,"duration":1},{"value":-1,"duration":0}],"name":"tightL"},{"colorFrame":[],"displayFrame":[{"value":-1,"duration":1},{"value":-1,"duration":0}],"name":"footR"},{"colorFrame":[],"displayFrame":[{"value":-1,"duration":1},{"value":-1,"duration":0}],"name":"tightR"},{"colorFrame":[],"displayFrame":[{"value":-1,"duration":1},{"value":-1,"duration":0}],"name":"tight"},{"colorFrame":[],"displayFrame":[{"value":6,"duration":1},{"value":6,"duration":0}],"name":"body"},{"colorFrame":[],"displayFrame":[{"value":-1,"duration":1},{"value":-1,"duration":0}],"name":"handR"},{"colorFrame":[],"displayFrame":[{"value":-1,"duration":1},{"value":-1,"duration":0}],"name":"armR"},{"colorFrame":[],"displayFrame":[{"value":-1,"duration":1},{"value":-1,"duration":0}],"name":"head"}],"ffd":[],"bone":[{"rotateFrame":[],"scaleFrame":[],"name":"root","translateFrame":[]},{"rotateFrame":[],"scaleFrame":[],"name":"body","translateFrame":[]},{"rotateFrame":[],"scaleFrame":[],"name":"bone","translateFrame":[]},{"rotateFrame":[],"scaleFrame":[],"name":"armR","translateFrame":[]},{"rotateFrame":[],"scaleFrame":[],"name":"head","translateFrame":[]},{"rotateFrame":[],"scaleFrame":[],"name":"armL","translateFrame":[]},{"rotateFrame":[],"scaleFrame":[],"name":"tightL","translateFrame":[]},{"rotateFrame":[],"scaleFrame":[],"name":"tightR","translateFrame":[]},{"rotateFrame":[],"scaleFrame":[],"name":"handL","translateFrame":[]},{"rotateFrame":[],"scaleFrame":[],"name":"handR","translateFrame":[]},{"rotateFrame":[],"scaleFrame":[],"name":"footR","translateFrame":[]},{"rotateFrame":[],"scaleFrame":[],"name":"footL","translateFrame":[]}],"name":"girlYellow_left","duration":1},{"ik":[],"frame":[],"playTimes":0,"slot":[{"colorFrame":[],"displayFrame":[{"value":-1,"duration":1},{"value":-1,"duration":0}],"name":"handL"},{"colorFrame":[],"displayFrame":[{"value":-1,"duration":1},{"value":-1,"duration":0}],"name":"armL"},{"colorFrame":[],"displayFrame":[{"value":-1,"duration":1},{"value":-1,"duration":0}],"name":"footL"},{"colorFrame":[],"displayFrame":[{"value":-1,"duration":1},{"value":-1,"duration":0}],"name":"tightL"},{"colorFrame":[],"displayFrame":[{"value":-1,"duration":1},{"value":-1,"duration":0}],"name":"footR"},{"colorFrame":[],"displayFrame":[{"value":-1,"duration":1},{"value":-1,"duration":0}],"name":"tightR"},{"colorFrame":[],"displayFrame":[{"value":-1,"duration":1},{"value":-1,"duration":0}],"name":"tight"},{"colorFrame":[],"displayFrame":[{"value":7,"duration":1},{"value":7,"duration":0}],"name":"body"},{"colorFrame":[],"displayFrame":[{"value":-1,"duration":1},{"value":-1,"duration":0}],"name":"handR"},{"colorFrame":[],"displayFrame":[{"value":-1,"duration":1},{"value":-1,"duration":0}],"name":"armR"},{"colorFrame":[],"displayFrame":[{"value":-1,"duration":1},{"value":-1,"duration":0}],"name":"head"}],"ffd":[],"bone":[{"rotateFrame":[],"scaleFrame":[],"name":"root","translateFrame":[]},{"rotateFrame":[],"scaleFrame":[],"name":"body","translateFrame":[]},{"rotateFrame":[],"scaleFrame":[],"name":"bone","translateFrame":[]},{"rotateFrame":[],"scaleFrame":[],"name":"armR","translateFrame":[]},{"rotateFrame":[],"scaleFrame":[],"name":"head","translateFrame":[]},{"rotateFrame":[],"scaleFrame":[],"name":"armL","translateFrame":[]},{"rotateFrame":[],"scaleFrame":[],"name":"tightL","translateFrame":[]},{"rotateFrame":[],"scaleFrame":[],"name":"tightR","translateFrame":[]},{"rotateFrame":[],"scaleFrame":[],"name":"handL","translateFrame":[]},{"rotateFrame":[],"scaleFrame":[],"name":"handR","translateFrame":[]},{"rotateFrame":[],"scaleFrame":[],"name":"footR","translateFrame":[]},{"rotateFrame":[],"scaleFrame":[],"name":"footL","translateFrame":[]}],"name":"girlYellow_right","duration":1}],"bone":[{"name":"root","transform":{"y":-79.45}},{"length":41,"transform":{"y":-9.5,"skX":-90.8323,"skY":-90.8323},"parent":"root","name":"body"},{"length":11,"transform":{"y":9.7,"skX":90,"skY":90,"x":0.45},"parent":"root","name":"bone"},{"length":30,"transform":{"y":30.7029,"skX":169.7641,"skY":169.7641,"x":30.9573},"parent":"body","name":"armR"},{"length":59,"transform":{"y":3.533,"skX":0.2584,"skY":0.2584,"x":43.5533},"parent":"body","name":"head"},{"length":24,"transform":{"y":-23.9492,"skX":-176.4693,"skY":-176.4693,"x":34.6515},"parent":"body","name":"armL"},{"length":31,"transform":{"y":9.65,"skX":2.6356,"skY":2.6356,"x":1.95},"parent":"bone","name":"tightL"},{"length":34,"transform":{"y":-17.95,"skX":-5.7189,"skY":-5.7189,"x":2.4},"parent":"bone","name":"tightR"},{"length":29,"transform":{"y":-2.3497,"skX":-6.3773,"skY":-6.3773,"x":24.3664},"parent":"armL","name":"handL"},{"length":35,"transform":{"y":1.9382,"skX":-4.3377,"skY":-4.3377,"x":31.0046},"parent":"armR","name":"handR"},{"length":21,"transform":{"y":-1.7603,"skX":-2.0342,"skY":-2.0342,"x":40.6276},"parent":"tightR","name":"footR"},{"length":27,"transform":{"y":3.0365,"skX":-12.9499,"skY":-12.9499,"x":29.7211},"parent":"tightL","name":"footL"}],"aabb":{"width":105,"y":-225.38876651982378,"height":225.25,"x":-52.5},"slot":[{"name":"handL","parent":"handL","color":{}},{"z":1,"name":"armL","parent":"armL","color":{}},{"z":2,"name":"footL","parent":"footL","color":{}},{"z":3,"name":"tightL","parent":"tightL","color":{}},{"z":4,"name":"footR","parent":"footR","color":{}},{"z":5,"name":"tightR","parent":"tightR","color":{}},{"z":6,"name":"tight","parent":"root","color":{}},{"z":7,"name":"body","parent":"body","color":{}},{"z":8,"name":"handR","parent":"handR","color":{}},{"z":9,"name":"armR","parent":"armR","color":{}},{"z":10,"name":"head","parent":"head","color":{}}],"name":"Armature","frameRate":24}],"name":"mathadventurecharaYELLOW","version":"5.5"}