{"skeleton":{"hash":"Tci8a9vh/y4","spine":"4.0.59","x":-69,"y":0.45,"width":132.01,"height":261.01,"images":"../library/","audio":""},"bones":[{"name":"root","y":79.45},{"name":"body","parent":"root","length":41,"rotation":90.83,"y":9.5},{"name":"bone","parent":"root","length":11,"rotation":-90,"x":0.45,"y":-9.7},{"name":"armR","parent":"body","length":30,"rotation":-169.76,"x":30.96,"y":-30.7},{"name":"head","parent":"body","length":59,"rotation":-0.26,"x":43.55,"y":-3.53},{"name":"armL","parent":"body","length":24,"rotation":176.47,"x":34.65,"y":23.95},{"name":"tightL","parent":"bone","length":31,"rotation":-2.64,"x":1.95,"y":-9.65},{"name":"tightR","parent":"bone","length":34,"rotation":5.72,"x":2.4,"y":17.95},{"name":"handL","parent":"armL","length":29,"rotation":6.38,"x":24.37,"y":2.35},{"name":"handR","parent":"armR","length":35,"rotation":4.34,"x":31,"y":-1.94},{"name":"footR","parent":"tightR","length":21,"rotation":2.03,"x":40.63,"y":1.76},{"name":"footL","parent":"tightL","length":27,"rotation":12.95,"x":29.72,"y":-3.04}],"slots":[{"name":"head","bone":"head","attachment":"char boy for dragonbones/head"},{"name":"handL","bone":"handL","attachment":"char boy for dragonbones/handL"},{"name":"armL","bone":"armL","attachment":"char boy for dragonbones/armL"},{"name":"footL","bone":"footL","attachment":"char boy for dragonbones/footL"},{"name":"tightL","bone":"tightL","attachment":"char boy for dragonbones/tightL"},{"name":"footR","bone":"footR","attachment":"char boy for dragonbones/footR"},{"name":"tightR","bone":"tightR","attachment":"char boy for dragonbones/tightR"},{"name":"tight","bone":"root","attachment":"char boy for dragonbones/tight"},{"name":"body","bone":"body","attachment":"char boy for dragonbones/body"},{"name":"handR","bone":"handR","attachment":"char boy for dragonbones/handR"},{"name":"armR","bone":"armR","attachment":"char boy for dragonbones/armR"}],"skins":[{"name":"default","attachments":{"armL":{"char boy for dragonbones/armL":{"x":10.78,"y":0.71,"rotation":92.7,"width":20,"height":32},"char boy forward/handR_foward":{"x":24.35,"y":-0.58,"rotation":92.7,"width":23,"height":70},"girlRed for dragonbones/armL":{"x":16.82,"y":3.24,"rotation":92.7,"width":12,"height":20},"girlRed forward/handR_foward":{"x":23.35,"y":6.81,"rotation":92.7,"width":18,"height":52}},"armR":{"char boy for dragonbones/armR":{"x":13.48,"y":0.42,"rotation":78.93,"width":23,"height":38},"char boy forward/handL_foward":{"x":24.73,"y":-1.96,"rotation":78.93,"width":27,"height":74},"girlRed for dragonbones/armR":{"x":15.82,"y":-7.94,"rotation":78.93,"width":14,"height":19},"girlRed forward/handL_foward":{"x":22.76,"y":-3.42,"rotation":78.93,"width":25,"height":60}},"body":{"char boy for dragonbones/body":{"x":19.91,"y":-6.04,"rotation":-90.83,"width":68,"height":59},"char boy forward/body_foward":{"x":27.83,"y":4.77,"rotation":-90.83,"width":68,"height":63},"char boy left/left":{"x":36.49,"y":-12.12,"rotation":-90.83,"width":179,"height":252},"char boy right/right":{"x":36.36,"y":-12.12,"rotation":-90.83,"width":179,"height":252},"girlRed for dragonbones/body":{"x":14.04,"y":-3.7,"rotation":-90.83,"width":56,"height":52},"girlRed forward/body_foward":{"x":26.58,"y":-5.39,"rotation":-90.83,"width":53,"height":51},"girlRed left/left":{"x":8.95,"y":-0.13,"rotation":-90.83,"width":184,"height":196},"girlRed right/right":{"x":9.38,"y":-0.14,"rotation":-90.83,"width":184,"height":196}},"footL":{"char boy for dragonbones/footL":{"x":16.28,"y":6.79,"rotation":79.69,"width":35,"height":33},"girlRed for dragonbones/footL":{"x":3.37,"y":7.61,"rotation":79.69,"width":27,"height":37}},"footR":{"char boy for dragonbones/footR":{"x":11.67,"y":6.79,"rotation":82.25,"width":36,"height":32},"girlRed for dragonbones/footR":{"x":-5.5,"y":1.8,"rotation":82.25,"width":30,"height":39}},"handL":{"char boy for dragonbones/handL":{"x":18.61,"y":-0.45,"rotation":86.32,"width":17,"height":41},"girlRed for dragonbones/handL":{"x":15.48,"y":3.01,"rotation":86.32,"width":18,"height":37}},"handR":{"char boy for dragonbones/handR":{"x":16.6,"y":0.56,"rotation":74.59,"width":25,"height":43},"girlRed for dragonbones/handR":{"x":9.4,"y":-7.32,"rotation":74.59,"width":22,"height":47}},"head":{"char boy for dragonbones/head":{"x":62.46,"y":5.27,"rotation":-90.57,"width":132,"height":133},"char boy forward/head_foward":{"x":64.62,"y":-4.07,"rotation":-90.57,"width":130,"height":146},"girlRed for dragonbones/head":{"x":43.67,"y":17.22,"rotation":-90.57,"width":119,"height":112},"girlRed forward/head_foward":{"x":54.37,"y":-18.9,"rotation":-90.57,"width":120,"height":115}},"tight":{"char boy for dragonbones/tight":{"x":5.5,"y":-6.75,"width":52,"height":27},"char boy forward/foot_foward":{"x":-5.18,"y":-33.25,"width":78,"height":91},"girlRed for dragonbones/tight":{"x":2.99,"y":-5.9,"width":47,"height":27},"girlRed forward/foot_foward":{"x":-0.74,"y":-20.34,"width":65,"height":78}},"tightL":{"char boy for dragonbones/tightL":{"x":16.62,"y":-0.04,"rotation":92.64,"width":28,"height":37},"girlRed for dragonbones/tightL":{"x":7.52,"y":-0.21,"rotation":92.64,"width":23,"height":32}},"tightR":{"char boy for dragonbones/tightR":{"x":19.86,"y":1.13,"rotation":84.28,"width":31,"height":45},"girlRed for dragonbones/tightR":{"x":10.09,"y":-5.19,"rotation":84.28,"width":25,"height":30}}}}],"animations":{"boyRed_idle1":{"bones":{"body":{"translate":[{},{"time":0.5,"y":-1.94},{"time":1}]},"armR":{"rotate":[{},{"time":0.5,"value":-3.82},{"time":1}]},"head":{"translate":[{},{"time":0.5,"x":-1.45,"y":0.02},{"time":1}]},"armL":{"rotate":[{},{"time":0.5,"value":5.84},{"time":1}]}},"drawOrder":[{"offsets":[{"slot":"tight","offset":1}]}]},"boyRed_idle2":{"slots":{"armL":{"attachment":[{"name":"char boy forward/handR_foward"}]},"armR":{"attachment":[{"name":"char boy forward/handL_foward"}]},"body":{"attachment":[{"name":"char boy forward/body_foward"}]},"footL":{"attachment":[{"name":null}]},"footR":{"attachment":[{"name":null}]},"handL":{"attachment":[{"name":null}]},"handR":{"attachment":[{"name":null}]},"head":{"attachment":[{"name":"char boy forward/head_foward"}]},"tight":{"attachment":[{"name":"char boy forward/foot_foward"}]},"tightL":{"attachment":[{"name":null}]},"tightR":{"attachment":[{"name":null}]}},"bones":{"head":{"translate":[{},{"time":0.5,"x":-0.27},{"time":1}]},"armL":{"rotate":[{},{"time":0.5,"value":5.84},{"time":1}]},"body":{"translate":[{},{"time":0.5,"y":-1.94},{"time":1}]},"armR":{"rotate":[{},{"time":0.5,"value":-3.82},{"time":1}]}},"drawOrder":[{"offsets":[{"slot":"tight","offset":1}]}]},"boyRed_left":{"slots":{"armL":{"attachment":[{"name":null}]},"armR":{"attachment":[{"name":null}]},"body":{"attachment":[{"name":"char boy left/left"}]},"footL":{"attachment":[{"name":null}]},"footR":{"attachment":[{"name":null}]},"handL":{"attachment":[{"name":null}]},"handR":{"attachment":[{"name":null}]},"head":{"attachment":[{"name":null}]},"tight":{"attachment":[{"name":null}]},"tightL":{"attachment":[{"name":null}]},"tightR":{"attachment":[{"name":null}]}}},"boyRed_right":{"slots":{"armL":{"attachment":[{"name":null}]},"armR":{"attachment":[{"name":null}]},"body":{"attachment":[{"name":"char boy right/right"}]},"footL":{"attachment":[{"name":null}]},"footR":{"attachment":[{"name":null}]},"handL":{"attachment":[{"name":null}]},"handR":{"attachment":[{"name":null}]},"head":{"attachment":[{"name":null}]},"tight":{"attachment":[{"name":null}]},"tightL":{"attachment":[{"name":null}]},"tightR":{"attachment":[{"name":null}]}}},"boyRed_run":{"bones":{"root":{"translate":[{"y":-9.93},{"time":0.125,"y":-1.57},{"time":0.25,"y":-10.32},{"time":0.375,"y":-3.62},{"time":0.5,"y":-9.93}]},"body":{"rotate":[{"value":-15.98},{"time":0.5,"value":-17.8}],"translate":[{"y":-3.96},{"time":0.125,"y":-3.05},{"time":0.25,"y":-4.72},{"time":0.375,"y":-3.43},{"time":0.5,"y":-4.98},{}]},"armR":{"rotate":[{"value":-48.69},{"time":0.25,"value":26.11},{"time":0.5,"value":-48.69}]},"head":{"rotate":[{"value":-8.04},{"time":0.25,"value":-1.81},{"time":0.5,"value":-8.04}],"translate":[{"x":-0.5,"y":2.67},{}]},"armL":{"rotate":[{"value":31.63},{"time":0.25,"value":-38.17},{"time":0.5,"value":31.63}],"translate":[{"x":1.61,"y":-8.6},{}]},"tightL":{"rotate":[{"value":-22.08},{"time":0.125,"value":17.56},{"time":0.25,"value":61.16},{"time":0.375,"value":10.49},{"time":0.5,"value":-22.08}],"translate":[{"y":0.76},{"time":0.125,"x":-1.71,"y":-1.03},{"time":0.25,"y":-5.79},{"time":0.375,"x":-2.05,"y":-0.31},{"time":0.5,"y":0.76},{}]},"tightR":{"rotate":[{"value":34.99},{"time":0.125,"value":-3.66},{"time":0.25,"value":-49.46},{"time":0.375,"value":-14.03},{"time":0.5,"value":34.99}],"translate":[{"curve":"stepped"},{"time":0.125,"x":-1.71},{"time":0.25,"y":3.31},{"time":0.375,"x":-0.68,"y":1.03},{}]},"footR":{"rotate":[{"value":-15.7},{"time":0.125,"value":0.31},{"time":0.25,"value":-27.96},{"time":0.5,"value":-15.7}],"translate":[{"curve":"stepped"},{"time":0.375,"x":-2.03,"y":-0.3},{}]},"handR":{"rotate":[{"value":27.35}],"translate":[{"x":-1.43,"y":0.25},{}]},"handL":{"rotate":[{"value":56.01}],"translate":[{"x":-3.02,"y":-2.87},{}]},"footL":{"rotate":[{"value":-28.56},{"time":0.125,"value":-36.32},{"time":0.25,"value":-14.93},{"time":0.375,"value":-11.35},{"time":0.5,"value":-28.56}],"translate":[{"x":-1.03,"y":2.24},{}]}},"drawOrder":[{"offsets":[{"slot":"tight","offset":1}]}]},"girlRed_idle1":{"slots":{"armL":{"attachment":[{"name":"girlRed for dragonbones/armL"}]},"armR":{"attachment":[{"name":"girlRed for dragonbones/armR"}]},"body":{"attachment":[{"name":"girlRed for dragonbones/body"}]},"footL":{"attachment":[{"name":"girlRed for dragonbones/footL"}]},"footR":{"attachment":[{"name":"girlRed for dragonbones/footR"}]},"handR":{"attachment":[{"name":"girlRed for dragonbones/handR"}]},"head":{"attachment":[{"name":"girlRed for dragonbones/head"}]},"tight":{"attachment":[{"name":"girlRed for dragonbones/tight"}]},"tightL":{"attachment":[{"name":"girlRed for dragonbones/tightL"}]},"tightR":{"attachment":[{"name":"girlRed for dragonbones/tightR"}]}},"bones":{"head":{"translate":[{},{"time":0.5,"x":-1.45,"y":0.02},{"time":1}]},"armL":{"rotate":[{},{"time":0.5,"value":5.84},{"time":1}]},"root":{"translate":[{"y":-13.03}]},"body":{"translate":[{},{"time":0.5,"y":-1.94},{"time":1}]},"armR":{"rotate":[{},{"time":0.5,"value":-3.82},{"time":1}]},"handL":{"translate":[{"x":-2.74,"y":4.23}]}}},"girlRed_idle2":{"slots":{"armL":{"attachment":[{"name":"girlRed forward/handR_foward"}]},"armR":{"attachment":[{"name":"girlRed forward/handL_foward"}]},"body":{"attachment":[{"name":"girlRed forward/body_foward"}]},"footL":{"attachment":[{"name":null}]},"footR":{"attachment":[{"name":null}]},"handL":{"attachment":[{"name":null}]},"handR":{"attachment":[{"name":null}]},"head":{"attachment":[{"name":"girlRed forward/head_foward"}]},"tight":{"attachment":[{"name":"girlRed forward/foot_foward"}]},"tightL":{"attachment":[{"name":null}]},"tightR":{"attachment":[{"name":null}]}},"bones":{"head":{"translate":[{},{"time":0.5,"x":-0.27},{"time":1}]},"armL":{"rotate":[{},{"time":0.5,"value":5.84},{"time":1}]},"root":{"translate":[{"y":-20.28}]},"body":{"translate":[{},{"time":0.5,"y":-1.94},{"time":1}]},"armR":{"rotate":[{},{"time":0.5,"value":-3.82},{"time":1}]}},"drawOrder":[{"offsets":[{"slot":"head","offset":10}]}]},"girlRed_left":{"slots":{"armL":{"attachment":[{"name":null}]},"armR":{"attachment":[{"name":null}]},"body":{"attachment":[{"name":"girlRed left/left"}]},"footL":{"attachment":[{"name":null}]},"footR":{"attachment":[{"name":null}]},"handL":{"attachment":[{"name":null}]},"handR":{"attachment":[{"name":null}]},"head":{"attachment":[{"name":null}]},"tight":{"attachment":[{"name":null}]},"tightL":{"attachment":[{"name":null}]},"tightR":{"attachment":[{"name":null}]}}},"girlRed_right":{"slots":{"armL":{"attachment":[{"name":null}]},"armR":{"attachment":[{"name":null}]},"body":{"attachment":[{"name":"girlRed right/right"}]},"footL":{"attachment":[{"name":null}]},"footR":{"attachment":[{"name":null}]},"handL":{"attachment":[{"name":null}]},"handR":{"attachment":[{"name":null}]},"head":{"attachment":[{"name":null}]},"tight":{"attachment":[{"name":null}]},"tightL":{"attachment":[{"name":null}]},"tightR":{"attachment":[{"name":null}]}}},"girlRed_run":{"slots":{"armL":{"attachment":[{"name":"girlRed for dragonbones/armL"}]},"armR":{"attachment":[{"name":"girlRed for dragonbones/armR"}]},"body":{"attachment":[{"name":"girlRed for dragonbones/body"}]},"footL":{"attachment":[{"name":"girlRed for dragonbones/footL"}]},"footR":{"attachment":[{"name":"girlRed for dragonbones/footR"}]},"handR":{"attachment":[{"name":"girlRed for dragonbones/handR"}]},"head":{"attachment":[{"name":"girlRed for dragonbones/head"}]},"tight":{"attachment":[{"name":"girlRed for dragonbones/tight"}]},"tightL":{"attachment":[{"name":"girlRed for dragonbones/tightL"}]},"tightR":{"attachment":[{"name":"girlRed for dragonbones/tightR"}]}},"bones":{"head":{"rotate":[{"value":-8.04},{"time":0.25,"value":-1.81},{"time":0.5,"value":-8.04}],"translate":[{"x":-0.5,"y":2.67},{}]},"armL":{"rotate":[{"value":31.63},{"time":0.25,"value":-38.17},{"time":0.5,"value":31.63}],"translate":[{"x":1.61,"y":-8.6},{}]},"footL":{"rotate":[{"value":-37.81},{"time":0.125,"value":-36.32},{"time":0.25,"value":-3.77},{"time":0.375,"value":-11.35},{"time":0.5,"value":-37.81}],"translate":[{"x":-2.18,"y":-5},{"time":0.125,"x":-0.53,"y":-4.51},{"time":0.25,"x":1.97,"y":-1.28},{"time":0.5,"x":-2.18,"y":-5},{}]},"tightL":{"rotate":[{"value":-22.08},{"time":0.125,"value":17.56},{"time":0.25,"value":38.83},{"time":0.375,"value":10.49},{"time":0.5,"value":-22.08}],"translate":[{"y":0.76},{"time":0.125,"x":-1.71,"y":-1.03},{"time":0.25,"x":-3.99,"y":-0.78},{"time":0.375,"x":-2.05,"y":-0.31},{"time":0.5,"y":0.76},{}]},"footR":{"rotate":[{"value":-15.7},{"time":0.125,"value":0.31},{"time":0.25,"value":-43},{"time":0.5,"value":-15.7}],"translate":[{"x":-3.92,"y":-5.03},{"time":0.125,"x":-0.62,"y":-0.63},{"time":0.25,"x":3.89,"y":-16.25},{"time":0.375,"x":3.4,"y":-7.9},{"time":0.5,"x":-3.92,"y":-5.03},{}]},"tightR":{"rotate":[{"value":34.99},{"time":0.125,"value":-3.66},{"time":0.25,"value":-22.38},{"time":0.375,"value":-14.03},{"time":0.5,"value":34.99}],"translate":[{"curve":"stepped"},{"time":0.125,"x":-1.71},{"time":0.25,"x":2.06,"y":2.38},{"time":0.375,"x":-0.68,"y":1.03},{}]},"body":{"rotate":[{"value":-15.98}],"translate":[{"y":-3.96},{"time":0.125,"x":-1.09,"y":-1.96},{"time":0.25,"y":-4.72},{"time":0.375,"y":-3.43},{"time":0.5,"y":-3.96},{}]},"root":{"translate":[{"y":-19.57},{"time":0.125,"y":-15.73},{"time":0.25,"y":-13.05,"curve":"stepped"},{"time":0.375,"y":-13.05},{"time":0.5,"y":-19.57}]},"handR":{"rotate":[{"value":27.35}],"translate":[{"x":-4.4,"y":2.43},{}]},"armR":{"rotate":[{"value":-48.69},{"time":0.25,"value":26.11},{"time":0.5,"value":-48.69}],"translate":[{"x":-1.92,"y":-6.47},{"time":0.125,"x":3.18,"y":-1.54},{"time":0.25,"x":3.84,"y":7.5},{"time":0.375,"x":1.66,"y":0.11},{"time":0.5,"x":-1.92,"y":-6.47},{}]},"handL":{"rotate":[{"value":56.01},{"time":0.125,"value":41.52},{"time":0.25,"value":27.03},{"time":0.5,"value":56.01}],"translate":[{"x":-3.02,"y":-2.87},{"time":0.125,"x":-4.02,"y":1.94},{"time":0.25,"x":-3.42,"y":2.2},{"time":0.5,"x":-3.02,"y":-2.87},{}]}}}}}